nl_philter-0.0.2.data/scripts/philter
philter/__init__.py
philter/commands.py
philter/dec.py
nl_philter-0.0.2.dist-info/LICENSE
nl_philter-0.0.2.dist-info/METADATA
nl_philter-0.0.2.dist-info/WHEEL
nl_philter-0.0.2.dist-info/top_level.txt
nl_philter-0.0.2.dist-info/RECORD
