Metadata-Version: 2.1
Name: nl-philter
Version: 0.0.2
Summary: cLUT/Cube toolkit for recording color transformations.
Home-page: UNKNOWN
Author: nonlogicaldev
License: UNKNOWN
Platform: UNKNOWN
Requires-Dist: numpy (>=1.16.2)
Requires-Dist: Pillow (>=6.2.0)
